programmering/__init__.py
programmering/programmering.py
programmering-0.0.1.dist-info/LICENCE
programmering-0.0.1.dist-info/METADATA
programmering-0.0.1.dist-info/WHEEL
programmering-0.0.1.dist-info/top_level.txt
programmering-0.0.1.dist-info/RECORD
