Metadata-Version: 2.1
Name: programmering
Version: 0.0.1
Summary: programmering
Author-email: matematikk <kontakt@matematikk.as>
Project-URL: Homepage, https://programmering.no
Project-URL: Issues, https://programmering.no
Classifier: Programming Language :: Python :: 3
Classifier: License :: OSI Approved :: MIT License
Classifier: Operating System :: OS Independent
Requires-Python: >=3.8
License-File: LICENCE
